VoxRasterLAS/Raster.py
VoxRasterLAS/Voxels.py
VoxRasterLAS/__init__.py
VoxRasterLAS/segmentation/__init__.py
VoxRasterLAS/segmentation/clouds_in_range.py
VoxRasterLAS/utils/__init__.py
VoxRasterLAS/utils/utils.py
VoxRasterLAS/utils/utils_cuda.py
voxrasterlas-0.1.0.dist-info/METADATA
voxrasterlas-0.1.0.dist-info/WHEEL
voxrasterlas-0.1.0.dist-info/licenses/COPYING
voxrasterlas-0.1.0.dist-info/RECORD
