Metadata-Version: 2.1
Name: VoxRasterLAS
Version: 0.1.0
Summary: Library for voxelising and rasterising LASPY objects
Project-URL: Repository, https://github.com/GeoTechUVigo/VoxRasterLAS
Author-email: Daniel Lamas Novoa <daniel.lamas.novoa@uvigo.gal>, GeoTech CINTEX UVigo <geotech@uvigo.gal>
License-File: COPYING
Classifier: License :: OSI Approved :: GNU Affero General Public License v3
Classifier: Operating System :: OS Independent
Classifier: Programming Language :: Python :: 3
Requires-Python: >=3.8
Requires-Dist: ismember==1.0.2
Requires-Dist: laspy<=2.5.1,>=2.0
Requires-Dist: numba==0.57
Requires-Dist: numpy
